orrin_sdk-0.0.11.dist-info/licenses/LICENSE
sdk/__init__.py
sdk/decorators.py
orrin_sdk-0.0.11.dist-info/METADATA
orrin_sdk-0.0.11.dist-info/WHEEL
orrin_sdk-0.0.11.dist-info/top_level.txt
orrin_sdk-0.0.11.dist-info/RECORD
