Metadata-Version: 2.4
Name: orrin-sdk
Version: 0.0.11
Summary: SDK for creating and registering custom Orrin apps
Author-email: Aidan White <ceo@stellr-company.com>
License: Copyright (c) 2026 Stellr, LLC. All rights reserved.
Project-URL: Homepage, https://stellr-company.com
Classifier: Programming Language :: Python :: 3
Classifier: License :: Other/Proprietary License
Classifier: Operating System :: OS Independent
Requires-Python: >=3.9
License-File: LICENSE
Dynamic: license-file
